forgevault/__init__.py
forgevault/cache.py
forgevault/cli.py
forgevault/client.py
forgevault/exceptions.py
forgevault/prompt.py
forgevault-0.1.4.dist-info/licenses/LICENSE
forgevault-0.1.4.dist-info/METADATA
forgevault-0.1.4.dist-info/WHEEL
forgevault-0.1.4.dist-info/entry_points.txt
forgevault-0.1.4.dist-info/top_level.txt
forgevault-0.1.4.dist-info/RECORD
