Metadata-Version: 2.4
Name: forgevault
Version: 0.1.4
Summary: ForgeVault SDK - Prompt management for production AI applications
Author-email: ForgeVault <forgevault.app@gmail.com>
Maintainer-email: ForgeVault <forgevault.app@gmail.com>
License: Proprietary
Project-URL: Homepage, https://forgevault.netlify.app
Project-URL: Documentation, https://forgevault.netlify.app/docs
Keywords: llm,prompt,ai,openai,anthropic,prompt-engineering,prompt-management
Classifier: Development Status :: 3 - Alpha
Classifier: Intended Audience :: Developers
Classifier: License :: Other/Proprietary License
Classifier: Operating System :: OS Independent
Classifier: Programming Language :: Python :: 3
Classifier: Programming Language :: Python :: 3.9
Classifier: Programming Language :: Python :: 3.10
Classifier: Programming Language :: Python :: 3.11
Classifier: Programming Language :: Python :: 3.12
Classifier: Topic :: Software Development :: Libraries :: Python Modules
Classifier: Topic :: Scientific/Engineering :: Artificial Intelligence
Requires-Python: >=3.9
License-File: LICENSE
Requires-Dist: httpx>=0.24.0
Provides-Extra: cli
Requires-Dist: typer>=0.9.0; extra == "cli"
Requires-Dist: rich>=13.0.0; extra == "cli"
Provides-Extra: dev
Requires-Dist: pytest>=7.0.0; extra == "dev"
Requires-Dist: pytest-asyncio>=0.21.0; extra == "dev"
Requires-Dist: pytest-cov>=4.0.0; extra == "dev"
Requires-Dist: black>=23.0.0; extra == "dev"
Requires-Dist: isort>=5.12.0; extra == "dev"
Requires-Dist: mypy>=1.0.0; extra == "dev"
Requires-Dist: typer>=0.9.0; extra == "dev"
Requires-Dist: rich>=13.0.0; extra == "dev"
Dynamic: license-file
